<?xml version="1.0" encoding="UTF-8"?>
<TEXTE_JURI_JUDI>
<META>
<META_COMMUN>
<ID>JURITEXT000034712090</ID>
<ANCIEN_ID/>
<ORIGINE>JURI</ORIGINE>
<URL>texte/juri/judi/JURI/TEXT/00/00/34/71/20/JURITEXT000034712090.xml</URL>
<NATURE>ORDONNANCE</NATURE>
</META_COMMUN>
<META_SPEC>
<META_JURI>
<TITRE>Cour d'appel de Paris, 9 mai 2017, 15/16722</TITRE>
<DATE_DEC>2017-05-09</DATE_DEC>
<JURIDICTION>Cour d'appel de Paris</JURIDICTION>
<NUMERO/>
<SOLUTION>Constate ou prononce le désistement d'instance et/ou d'action</SOLUTION>
</META_JURI>
<META_JURI_JUDI>
<NUMEROS_AFFAIRES>
<NUMERO_AFFAIRE>15/16722</NUMERO_AFFAIRE>
</NUMEROS_AFFAIRES>
<PUBLI_BULL publie="non"/>
<FORMATION>Pôle 3 - Chambre 4</FORMATION>

<FORM_DEC_ATT/>
<DATE_DEC_ATT/>
<SIEGE_APPEL>PARIS</SIEGE_APPEL>
<JURI_PREM/>
<LIEU_PREM/>
<DEMANDEUR/>
<DEFENDEUR/>
<PRESIDENT/>
<AVOCAT_GL/>
<AVOCATS/>
<RAPPORTEUR/>
</META_JURI_JUDI>
</META_SPEC>
</META>
<TEXTE>
<BLOC_TEXTUEL>
<CONTENU>
<br/>
<br/>
COUR D'APPEL DE PARIS<br/>
<br/>
Pôle 3 - Chambre 4<br/>
RG No: 15/16722<br/>
<br/>
Nature de l'acte de saisine : Déclaration d'appel valant inscription au rôle<br/>
Date de l'acte de saisine : 31 Juillet 2015<br/>
Date de saisine :  21 Août 2015<br/>
Nature de l'affaire :  Demande de modification des mesures provisoires - divorce -<br/>
Décision attaquée : no  14/04947 rendue par le Juge aux affaires familiales de Meaux le 16 Juin 2015<br/>
<br/>
Appelant :<br/>
 Monsieur Ghalem X..., représenté par Me Thierry BENKIMOUN, avocat au barreau de MEAUX<br/>
<br/>
<br/>
Intimée :<br/>
 Madame SALIMA Y... épouse X..., représentée par Me Nathalie MARTIN, avocat au barreau de PARIS, toque : C1669<br/>
(bénéficie d'une aide juridictionnelle Totale numéro 2015/047018 du 25/11/2015 accordée par le bureau d'aide juridictionnelle de PARIS)<br/>
<br/>
<br/>
<br/>
<br/>
ORDONNANCE DE DÉSISTEMENT ACCEPTÉ TOTAL<br/>
<br/>
<br/>
Nous, Anne GONGORA, magistrat en charge de la mise en état, <br/>
Assistée de Rima RAHMOUNI, adjoint faisant fonction de greffier,<br/>
<br/>
Vu les articles 400 et suivants, 769 et 907 du code de procédure civile,<br/>
<br/>
Attendu que l'appelant s'est désisté de son appel en date du 04 août 2016;<br/>
<br/>
Que l'intimé a accepté ce désistement en date du 09 octobre 2016 dans les termes de l'article 401 du Code de procédure civile ;<br/>
<br/>
Attendu que le désistement est parfait ;<br/>
<br/>
					PAR CES MOTIFS,<br/>
<br/>
Constatons l'extinction de l'instance et le dessaisissement de la Cour ;<br/>
<br/>
Disons que les frais de l'instance éteinte seront, sauf convention contraire, supportés par l'appelant.<br/>
<br/>
<br/>
<br/>
<br/>
								Paris, le 09 mai 2017<br/>
<br/>
Le greffier							Le magistrat en charge de la mise en état<br/>
<br/>
<br/>
<br/>
<br/>
Copie au dossier<br/>
Copie aux avocats<br/>
</CONTENU>
</BLOC_TEXTUEL>
<SOMMAIRE>
<SCT ID="1" TYPE="PRINCIPAL"/>
<SCT ID="1" TYPE="REFERENCE"/>
<ANA ID="1"/>
</SOMMAIRE>

<CITATION_JP>
<CONTENU>



</CONTENU>
</CITATION_JP>
</TEXTE>
<LIENS/>
</TEXTE_JURI_JUDI>
